{
  "name": "Arbitrum Tap Tap Game",
  "iconUrl": "https://arbitrumgame.vercel.app/arbitrum-logo.png",
  "subtitle": "Official Arbitrum Gaming Experience",
  "description": "Experience the future of Web3 gaming on Arbitrum! Tap to earn points, unlock exclusive NFTs at milestones, and compete on the global leaderboard. Built with Arbitrum's Layer 2 technology for fast, low-cost transactions.",
  "primaryCategory": "games",
  "imageUrl": "https://arbitrumgame.vercel.app/image.png",
  "splashImageUrl": "https://arbitrumgame.vercel.app/splash.png",
  "splashBackgroundColor": "#28a0f0",
  "tags": [
    "gaming",
    "arbitrum",
    "nft",
    "web3",
    "layer2",
    "defi",
    "blockchain"
  ],
  "tagline": "Tap, Earn, Mint on Arbitrum",
  "buttonTitle": "Play Arbitrum Game",
  "homeUrl": "https://arbitrumgame.vercel.app",
  "webhookUrl": "https://arbitrumgame.vercel.app/api/webhook",
  "metadata": {
    "version": "1.0.0",
    "developer": "Arbitrum Community",
    "website": "https://arbitrum.io",
    "support": "https://discord.gg/arbitrum",
    "privacyPolicy": "https://arbitrumgame.vercel.app/privacy",
    "termsOfService": "https://arbitrumgame.vercel.app/terms"
  }
}